pocket_recs/__init__.py
pocket_recs/cli.py
pocket_recs/config.py
pocket_recs/types.py
pocket_recs/api/__init__.py
pocket_recs/api/app.py
pocket_recs/offline/__init__.py
pocket_recs/offline/brand_pop.py
pocket_recs/offline/covis.py
pocket_recs/offline/embed.py
pocket_recs/offline/fit.py
pocket_recs/offline/index_ann.py
pocket_recs/offline/manifest.py
pocket_recs/offline/sessionize.py
pocket_recs/offline/train_ranker.py
pocket_recs/online/__init__.py
pocket_recs/online/ann_utils.py
pocket_recs/online/mmr.py
pocket_recs/online/reasons.py
pocket_recs/online/recommender.py
pocket_recs-0.1.0.dist-info/METADATA
pocket_recs-0.1.0.dist-info/WHEEL
pocket_recs-0.1.0.dist-info/entry_points.txt
pocket_recs-0.1.0.dist-info/licenses/LICENSE
pocket_recs-0.1.0.dist-info/RECORD
