Metadata-Version: 2.4
Name: pocket-recs
Version: 0.1.0
Summary: CPU-only hybrid recommender (co-vis + ANN + LightGBM) with tiny footprint.
Project-URL: Homepage, https://github.com/amjad/pocket-recs
Project-URL: Issues, https://github.com/amjad/pocket-recs/issues
Author-email: Amjad <amjadsaab.as.as@gmail.com>
License-Expression: Apache-2.0
License-File: LICENSE
Keywords: ANN,FAISS,LightGBM,hnsw,ranking,recommendation
Classifier: License :: OSI Approved :: Apache Software License
Classifier: Operating System :: OS Independent
Classifier: Programming Language :: Python :: 3
Requires-Python: >=3.9
Requires-Dist: duckdb>=1.0
Requires-Dist: lightgbm>=4.3
Requires-Dist: numpy>=1.24
Requires-Dist: polars>=1.5
Requires-Dist: pyarrow>=15
Requires-Dist: pydantic>=2.7
Requires-Dist: rich>=13.7
Requires-Dist: scikit-learn>=1.4
Requires-Dist: sentence-transformers>=3.0
Requires-Dist: typer>=0.12
Provides-Extra: ann
Requires-Dist: faiss-cpu>=1.8.0.post1; (platform_machine != 'aarch64' and sys_platform != 'win32') and extra == 'ann'
Requires-Dist: hnswlib>=0.8.0; extra == 'ann'
Provides-Extra: api
Requires-Dist: fastapi>=0.115; extra == 'api'
Requires-Dist: prometheus-client>=0.20; extra == 'api'
Requires-Dist: uvicorn[standard]>=0.30; extra == 'api'
Provides-Extra: dev
Requires-Dist: black>=24.8; extra == 'dev'
Requires-Dist: build; extra == 'dev'
Requires-Dist: mypy>=1.10; extra == 'dev'
Requires-Dist: pre-commit>=3.8; extra == 'dev'
Requires-Dist: pytest-benchmark>=4.0; extra == 'dev'
Requires-Dist: pytest>=8.2; extra == 'dev'
Requires-Dist: ruff>=0.6; extra == 'dev'
Requires-Dist: twine; extra == 'dev'
Provides-Extra: onnx
Requires-Dist: onnxruntime>=1.18; extra == 'onnx'
